completion/__init__.py
completion/apps.py
completion/exceptions.py
completion/handlers.py
completion/models.py
completion/services.py
completion/test_utils.py
completion/urls.py
completion/utilities.py
completion/waffle.py
completion/api/__init__.py
completion/api/permissions.py
completion/api/urls.py
completion/api/tests/__init__.py
completion/api/tests/test_permissions.py
completion/api/v1/__init__.py
completion/api/v1/urls.py
completion/api/v1/views.py
completion/api/v1/tests/__init__.py
completion/migrations/0001_initial.py
completion/migrations/0001_squashed_0003_learning_context.py
completion/migrations/0002_auto_20180125_1510.py
completion/migrations/0003_learning_context.py
completion/migrations/0004_rename_indexes.py
completion/migrations/__init__.py
completion/settings/__init__.py
completion/settings/common.py
completion/settings/test_settings.py
completion/tests/__init__.py
completion/tests/test_models.py
completion/tests/test_services.py
completion/tests/test_utilities.py
edx_completion-4.9.dist-info/licenses/LICENSE
edx_completion-4.9.dist-info/METADATA
edx_completion-4.9.dist-info/WHEEL
edx_completion-4.9.dist-info/entry_points.txt
edx_completion-4.9.dist-info/top_level.txt
edx_completion-4.9.dist-info/RECORD
