Metadata-Version: 2.4
Name: edx-completion
Version: 4.9
Summary: A library for tracking completion of blocks by learners in edX courses.
Home-page: https://github.com/openedx/completion
Author: edX
Author-email: oscm@edx.org
License: AGPL 3.0
Keywords: Django edx
Classifier: Development Status :: 3 - Alpha
Classifier: Framework :: Django
Classifier: Framework :: Django :: 4.2
Classifier: Framework :: Django :: 5.2
Classifier: Intended Audience :: Developers
Classifier: License :: OSI Approved :: GNU Affero General Public License v3 or later (AGPLv3+)
Classifier: Natural Language :: English
Classifier: Programming Language :: Python :: 3
Classifier: Programming Language :: Python :: 3.11
Classifier: Programming Language :: Python :: 3.12
License-File: LICENSE
Requires-Dist: Django
Requires-Dist: XBlock>=1.2.2
Requires-Dist: django-model-utils
Requires-Dist: djangorestframework
Requires-Dist: edx-drf-extensions>=1.11.0
Requires-Dist: edx-opaque-keys[django]
Requires-Dist: edx-toggles>=1.2.0
Requires-Dist: event-tracking
Requires-Dist: pytz
Requires-Dist: setuptools
Dynamic: author
Dynamic: author-email
Dynamic: classifier
Dynamic: description
Dynamic: home-page
Dynamic: keywords
Dynamic: license
Dynamic: license-file
Dynamic: requires-dist
Dynamic: summary
